{
  "default": {
    "video": "https://github.com/zlargon/res/releases/download/hunter/hunter_final_no_subtitles.mp4",
    "start_time": null,
    "end_time": null,
    "select_time": 15,
    "next": []
  },

  "begin": {
    "start_time": "00:00:00.00",
    "end_time": "00:00:00.00",
    "next": [
      "part 1"
    ]
  },

  "part 1": {
    "start_time": "00:00:00.00",
    "end_time": "00:04:41.32",
    "select_time": 9,
    "next": [
      "let sam quite",
      "let sam talk"
    ]
  },

  "let sam quite": {
    "start_time": "00:05:05.12",
    "end_time": "00:06:39.24",
    "next": [
      "part 2"
    ]
  },

  "let sam talk": {
    "start_time": "00:06:50.20",
    "end_time": "00:07:06.22",
    "next": [
      "part 2"
    ]
  },

  "part 2": {
    "start_time": "00:07:06.23",
    "end_time": "00:09:40.23",
    "select_time": 17,
    "next": [
      "put towel into sam's mouth",
      "put cloth into sam's mouth"
    ]
  },

  "put towel into sam's mouth": {
    "start_time": "00:09:57.39",
    "end_time": "00:13:55.29",
    "next": [
      "part 3"
    ]
  },

  "put cloth into sam's mouth": {
    "start_time": "00:14:25.51",
    "end_time": "00:14:43.42",
    "next": [
      "part 3"
    ]
  },

  "part 3": {
    "start_time": "00:14:43.43",
    "end_time": "00:15:39.20",
    "select_time": 15,
    "next": [
      "help ashley",
      "help jake",
      "help corey",
      "help sam"
    ]
  },

  "help ashley": {
    "start_time": "00:15:52.45",
    "end_time": "00:21:05.17"
  },

  "help jake": {
    "start_time": "00:21:09.04",
    "end_time": "00:31:19.25"
  },

  "help corey": {
    "start_time": "00:31:20.09",
    "end_time": "00:36:56.00"
  },

  "help sam": {
    "start_time": "00:37:01.15",
    "end_time": "00:41:16.48"
  }
}
